work_toto/__init__.py
work_toto/authentication.py
work_toto/cli.py
work_toto/permission.py
work_toto/work_toto.py
work_toto-0.1.0.dist-info/AUTHORS.rst
work_toto-0.1.0.dist-info/LICENSE
work_toto-0.1.0.dist-info/METADATA
work_toto-0.1.0.dist-info/WHEEL
work_toto-0.1.0.dist-info/entry_points.txt
work_toto-0.1.0.dist-info/top_level.txt
work_toto-0.1.0.dist-info/RECORD
